cameras_cli/__init__.py
cameras_cli-1.0.1.dist-info/METADATA
cameras_cli-1.0.1.dist-info/WHEEL
cameras_cli-1.0.1.dist-info/entry_points.txt
cameras_cli-1.0.1.dist-info/top_level.txt
cameras_cli-1.0.1.dist-info/RECORD
